mistify/__init__.py
mistify/_base/__init__.py
mistify/_base/_base.py
mistify/_functional/__init__.py
mistify/_functional/_dist.py
mistify/_functional/_factory.py
mistify/_functional/_grad.py
mistify/_functional/_join.py
mistify/_functional/_logic.py
mistify/_functional/_m.py
mistify/_functional/_set_ops.py
mistify/_functional/_shape.py
mistify/_functional/boolean/__init__.py
mistify/_functional/boolean/_functional.py
mistify/_functional/boolean/_generate.py
mistify/_functional/fuzzy/__init__.py
mistify/_functional/fuzzy/_functional.py
mistify/_functional/fuzzy/_generate.py
mistify/_functional/signed/__init__.py
mistify/_functional/signed/_functional.py
mistify/_functional/signed/_generate.py
mistify/fuzzify/__init__.py
mistify/fuzzify/_conversion/__init__.py
mistify/fuzzify/_conversion/_aggregate.py
mistify/fuzzify/_conversion/_conclude.py
mistify/fuzzify/_conversion/_converters.py
mistify/fuzzify/_conversion/_fuzzifiers.py
mistify/fuzzify/_conversion/_hypo.py
mistify/fuzzify/_conversion/_utils.py
mistify/fuzzify/_resp.py
mistify/fuzzify/_shapes/__init__.py
mistify/fuzzify/_shapes/_base.py
mistify/fuzzify/_shapes/_composite.py
mistify/fuzzify/_shapes/_gaussian.py
mistify/fuzzify/_shapes/_logistic.py
mistify/fuzzify/_shapes/_ramp.py
mistify/fuzzify/_shapes/_sigmoid.py
mistify/fuzzify/_shapes/_square.py
mistify/fuzzify/_shapes/_step.py
mistify/fuzzify/_shapes/_trapezoid.py
mistify/fuzzify/_shapes/_triangle.py
mistify/fuzzify/_shapes/_utils.py
mistify/infer/__init__.py
mistify/infer/_activate.py
mistify/infer/_neurons.py
mistify/infer/_noise.py
mistify/infer/_ops.py
mistify/infer/_shape.py
mistify/process/__init__.py
mistify/process/_fit.py
mistify/process/_m.py
mistify/process/_reverse.py
mistify/process/_table.py
mistify/process/_transformation.py
mistify/systems/__init__.py
mistify/systems/_anfis.py
mistify/utils/__init__.py
mistify/utils/_utils.py
mistify-0.0.1.dist-info/LICENSE
mistify-0.0.1.dist-info/METADATA
mistify-0.0.1.dist-info/WHEEL
mistify-0.0.1.dist-info/RECORD
