Metadata-Version: 2.1
Name: mistify
Version: 0.0.1
Summary: Neuro-fuzzy systems with PyTorch.
Home-page: https://github.com/short-greg/mistify
License: LICENSE
Author: Greg Short
Author-email: g.short@kurenai.waseda.jp
Requires-Python: >=3.8,<4.0
Classifier: License :: Other/Proprietary License
Classifier: Programming Language :: Python :: 3
Classifier: Programming Language :: Python :: 3.8
Classifier: Programming Language :: Python :: 3.9
Classifier: Programming Language :: Python :: 3.10
Classifier: Programming Language :: Python :: 3.11
Classifier: Programming Language :: Python :: 3.12
Requires-Dist: pandas (>=1,<2)
Requires-Dist: scipy (>=1.5,<2.0)
Requires-Dist: tqdm (>=4.0)
Project-URL: Documentation, https://mistify.readthedocs.com
Project-URL: Repository, https://github.com/short-greg/mistify
